axu/__init__.py
axu/turing.py
axu-0.1.0.dist-info/WHEEL
axu-0.1.0.dist-info/METADATA
axu-0.1.0.dist-info/RECORD
